{
  "annotations": {
    "changelogDate": "20240717021313"
  },
  "applications": ["gateway", "CanBo"],
  "databaseType": "sql",
  "dto": "mapstruct",
  "fields": [
    {
      "fieldName": "idQuyen",
      "fieldType": "Long"
    }
  ],
  "jpaMetamodelFiltering": true,
  "name": "CanBoQuyen",
  "relationships": [
    {
      "otherEntityName": "danhMucDonVi",
      "relationshipName": "idDonVi",
      "relationshipSide": "right",
      "relationshipType": "many-to-one"
    }
  ],
  "searchEngine": "no",
  "service": "serviceImpl",
  "skipServer": true
}
